LICENSE
README.md
setup.py
mureka_mcp/__init__.py
mureka_mcp/__main__.py
mureka_mcp/api.py
mureka_mcp.egg-info/PKG-INFO
mureka_mcp.egg-info/SOURCES.txt
mureka_mcp.egg-info/dependency_links.txt
mureka_mcp.egg-info/requires.txt
mureka_mcp.egg-info/top_level.txt
tests/test_api.py