Metadata-Version: 2.4
Name: mureka-mcp
Version: 0.0.2
Summary: The mcp server of Mureka.ai 
Author: wei.zhang
Author-email: zhangwei@singularity-ai.com
License: MIT
Keywords: ai generate music mureka mcp
Requires-Python: >=3.10
License-File: LICENSE
Requires-Dist: mcp>=1.6.0
Dynamic: author
Dynamic: author-email
Dynamic: description
Dynamic: description-content-type
Dynamic: keywords
Dynamic: license
Dynamic: license-file
Dynamic: requires-dist
Dynamic: requires-python
Dynamic: summary
